src/SAR_Controller.v
/*******************************************************************
*
* Module: SAR_Controller.v
* Project: Successive Approximation Register (SAR) ADC Controller
* Author: Ahmed Refaay - refaay@aucegypt.edu
* Description: Full Successive Approximation Register (SAR) ADC Controller Circuit
*
* Change history: 02/17/18 – Created module
*                 02/23/18 – Finished module
*
**********************************************************************/

`include "src/global_numerics.v"

module SAR_Controller(clk, rst, go, cmp, sample, value, valid, result);
    parameter N = 8; // number of bits
    parameter S = 3; // number of sample cycles
    
    input wire [0:0] clk; // global clk
    input wire [0:0] rst; // global reset
    
    input wire [0:0] go; // to start sampling
    input wire [0:0] cmp; // analog op-amp output
    output reg [0:0] sample; // indicates that the conversion is in process
    output reg [N-1:0] value; // register to store the converted bits
    output reg [0:0] valid; // indicates that the conversion is finished
    output reg [N-1:0] result; // result output

    reg [4:0] counter; // 5-bits since the highest count is 16
    reg [3:0] counter2; // 4-bits for sample output control assuming the highest count is 15
    integer k;

    always @(posedge clk or negedge rst) begin
        if (~rst) begin
            value <= {1'b1, {(N-1){1'd0}}};
            result <= {N{1'd0}};
            valid <= 1'd0;
            counter <= 5'd0;
            counter2 <= 4'd0;
            sample <= 1'd0;
        end
        else begin
            if(go) begin // initialize and sample on
                value <= {1'b1, {(N-1){1'd0}}};
                result <= result;
                valid <= 1'b0;
                counter <= 5'd0;
                counter2 <= 4'd1;
                sample <= 1'b1;
            end
            else begin
                if(sample) begin // sample till count
                    counter2 <= counter2 + 4'd1;
                    valid <= 1'b0;
                    value <= {1'b1, {(N-1){1'd0}}};
                    result <= result;
                    counter <= 5'd1;
                    if(counter2 >= S) begin
                        sample <= 1'd0;
                    end
                    else begin
                        sample <= sample;
                    end
                end
                else begin // begin actual conversion
                    counter2 <= 4'd0;
                    sample <= 1'd0;
                    if(counter >= N) begin // end conversion
                        valid <= 1'b1;
                        value <= value;
                        result <= value;
                        counter <= counter;
                    end
                    else begin
                        counter <= counter + 5'd1;
                        valid <= 1'b0;
                        result <= result;
                        for(k=0; k<N; k=k+1) begin // conversion algorithm
                            if(k == N-counter) 
                                value[k] <= cmp;
                            else if(k == N-counter-1) 
                                value[k] <= 1'b1;
                            else 
                                value[k] <= value[k];
                        end
                    end
                end 
            end
        end
    end
endmodule

src/SAR_Controller_tb.v
// file: SAR_Controller_tb.v
// author: @refaay
// Testbench for SAR_Controller

`timescale 1ns/1ns

module SAR_Controller_tb;

	//Inputs
	reg [0: 0] clk;
	reg [0: 0] rst;
	reg [0: 0] go;
	reg [0: 0] cmp;


	//Outputs
	wire  [0:0] sample;
	wire [7: 0] value;
	wire [0: 0] valid;
	wire  [8-1:0] result;


    //For Testbench
    wire [7:0] analog = 8'd167;
    wire err;
    
    assign err =  (result != analog) & valid; // self-checking
    
	//Instantiation of Unit Under Test
	SAR_Controller uut (
		.clk(clk),
		.rst(rst),
		.go(go),
		.cmp(cmp),
		.sample(sample),
		.value(value),
		.valid(valid),
		.result(result)
	);

    always #2 clk = !clk;
    
	initial begin
	//Inputs initialization
		clk = 1'b0;
		rst = 1'b0;
		go = 1'b0;

		#12;
		rst = 1'b1;
		go = 1'b1;
		
		#4;
		go = 1'b0;
		
        #400;
        go = 1'b1;

		#4;
		go = 1'b0;
	end

    always @(negedge clk) begin // OP-AMP
        cmp <= (analog>value);
    end

endmodule

build (read-only)/SAR_Controller_tb.vcd
$date
	Fri Feb 23 18:54:26 2018
$end
$version
	Icarus Verilog
$end
$timescale
	1ns
$end
$scope module SAR_Controller_tb $end
$var wire 8 ! analog [7:0] $end
$var wire 1 " err $end
$var wire 8 # value [7:0] $end
$var wire 1 $ valid $end
$var wire 1 % sample $end
$var wire 8 & result [7:0] $end
$var reg 1 ' clk $end
$var reg 1 ( cmp $end
$var reg 1 ) go $end
$var reg 1 * rst $end
$scope module uut $end
$var wire 1 ' clk $end
$var wire 1 ( cmp $end
$var wire 1 ) go $end
$var wire 1 * rst $end
$var reg 5 + counter [4:0] $end
$var reg 4 , counter2 [3:0] $end
$var reg 8 - result [7:0] $end
$var reg 1 % sample $end
$var reg 1 $ valid $end
$var reg 8 . value [7:0] $end
$var integer 32 / k [31:0] $end
$upscope $end
$upscope $end
$enddefinitions $end
#0
$dumpvars
bx /
b10000000 .
b0 -
b0 ,
b0 +
0*
0)
x(
0'
b0 &
0%
0$
b10000000 #
0"
b10100111 !
$end
#2
1'
#4
1(
0'
#6
1'
#8
0'
#10
1'
#12
0'
1)
1*
#14
1%
b1 ,
1'
#16
0'
0)
#18
b1 +
b10 ,
1'
#20
0'
#22
b11 ,
1'
#24
0'
#26
0%
b100 ,
1'
#28
0'
#30
b11000000 #
b11000000 .
b10 +
b0 ,
b1000 /
1'
#32
0(
0'
#34
b10100000 #
b10100000 .
b11 +
b1000 /
1'
#36
1(
0'
#38
b10110000 #
b10110000 .
b100 +
b1000 /
1'
#40
0(
0'
#42
b10101000 #
b10101000 .
b101 +
b1000 /
1'
#44
0'
#46
b10100100 #
b10100100 .
b110 +
b1000 /
1'
#48
1(
0'
#50
b10100110 #
b10100110 .
b111 +
b1000 /
1'
#52
0'
#54
b10100111 #
b10100111 .
b1000 +
b1000 /
1'
#56
0(
0'
#58
b10100111 &
b10100111 -
1$
1'
